BinMSGUI/__init__.py
BinMSGUI/__main__.py
BinMSGUI/main.py
BinMSGUI/core/ChooseDirectory.py
BinMSGUI/core/Tint_Matlab.py
BinMSGUI/core/__init__.py
BinMSGUI/core/addSessions.py
BinMSGUI/core/batch_functions.py
BinMSGUI/core/bin2mda.py
BinMSGUI/core/convert_position.py
BinMSGUI/core/cut_creation.py
BinMSGUI/core/default_parameters.py
BinMSGUI/core/eeg_conversion.py
BinMSGUI/core/filtering.py
BinMSGUI/core/gui_utils.py
BinMSGUI/core/intan_mountainsort.py
BinMSGUI/core/intan_rhd_functions.py
BinMSGUI/core/mdaSort.py
BinMSGUI/core/mountainsort_functions.py
BinMSGUI/core/readBin.py
BinMSGUI/core/readMDA.py
BinMSGUI/core/rhd_utils.py
BinMSGUI/core/set_conversion.py
BinMSGUI/core/tetrode_conversion.py
BinMSGUI/core/utils.py
BinMSGUI/core/wsl_terminal.py
BinMSGUI/img/GEBA_Logo.png
BinMSGUI-1.0.4.dist-info/LICENSE
BinMSGUI-1.0.4.dist-info/METADATA
BinMSGUI-1.0.4.dist-info/WHEEL
BinMSGUI-1.0.4.dist-info/top_level.txt
BinMSGUI-1.0.4.dist-info/RECORD
