Metadata-Version: 2.1
Name: BinMSGUI
Version: 1.0.4
Summary: BinMSGUI, sorts .bin data through MountainSort and exports as Tint format.
Home-page: https://github.com/HussainiLab/BinMSGUI.git
Author: Geoffrey Barrett
Author-email: geoffrey.m.barrett@gmail.com
License: UNKNOWN
Platform: UNKNOWN
Classifier: Programming Language :: Python :: 3.7 
Classifier: License :: OSI Approved :: GNU General Public License v3 (GPLv3) 
Classifier: Operating System :: OS Independent
Requires-Dist: PyQt5
Requires-Dist: numpy
Requires-Dist: scipy
Requires-Dist: matplotlib
Requires-Dist: jupyter
